drag_dash/DragDash.py
drag_dash/__init__.py
drag_dash/_imports_.py
drag_dash/drag_dash.min.js
drag_dash/drag_dash.min.js.map
drag_dash/metadata.json
drag_dash/package-info.json
drag_dash-0.0.3.dist-info/LICENSE
drag_dash-0.0.3.dist-info/METADATA
drag_dash-0.0.3.dist-info/WHEEL
drag_dash-0.0.3.dist-info/top_level.txt
drag_dash-0.0.3.dist-info/RECORD
