Metadata-Version: 2.1
Name: drag-dash
Version: 0.0.3
Summary: drag dash objects
Author: Jin Ch <jin236248@gmail.com>
License: MIT
Classifier: Framework :: Dash
License-File: LICENSE
